[
  {
    "game_id": "BSN194504170",
    "date": "19450417",
    "game_number": "0",
    "day_of_week": "Tuesday",
    "start_time": "0",
    "DH_used_flag": "F",
    "day_night_flag": "D",
    "visiting_team": "NY1",
    "home_team": "BSN",
    "game_site": "BOS08",
    "vis_starting_pitcher": "voisb101",
    "home_starting_pitcher": "javea101",
    "home_plate_umpire": "mageg901",
    "first_base_umpire": "stewb901",
    "second_base_umpire": "dunnt901",
    "third_base_umpire": "henlb101",
    "left_field_umpire": "",
    "right_field_umpire": "",
    "attendance": "5021",
    "PS_scorer": "32",
    "translator": "Comly",
    "inputter": "Comly",
    "input_time": "2000/01/01 6:16PM",
    "edit_time": "",
    "how_scored": "1",
    "pitches_entered": "0",
    "temperature": "0",
    "wind_direction": "0",
    "wind_speed": "-1",
    "field_condition": "0",
    "precipitation": "0",
    "sky": "0",
    "time_of_game": "0",
    "number_of_innings": "9",
    "visitor_final_score": "11",
    "home_final_score": "6",
    "visitor_hits": "15",
    "home_hits": "12",
    "visitor_errors": "1",
    "home_errors": "0",
    "visitor_left_on_base": "9",
    "home_left_on_base": "11",
    "winning_pitcher": "voisb101",
    "losing_pitcher": "javea101",
    "save_for": "adama101",
    "GW_RBI": "",
    "visitor_batter_1": "ruckj101",
    "visitor_position_1": "8",
    "visitor_batter_2": "hausg101",
    "visitor_position_2": "4",
    "visitor_batter_3": "ott-m101",
    "visitor_position_3": "9",
    "visitor_batter_4": "filis101",
    "visitor_position_4": "7",
    "visitor_batter_5": "weinp101",
    "visitor_position_5": "3",
    "visitor_batter_6": "lombe101",
    "visitor_position_6": "2",
    "visitor_batter_7": "kerrb101",
    "visitor_position_7": "6",
    "visitor_batter_8": "reyen101",
    "visitor_position_8": "5",
    "visitor_batter_9": "voisb101",
    "visitor_position_9": "1",
    "home_batter_1": "culld101",
    "home_position_1": "6",
    "home_batter_2": "holmt101",
    "home_position_2": "7",
    "home_batter_3": "workc101",
    "home_position_3": "9",
    "home_batter_4": "mackj101",
    "home_position_4": "3",
    "home_batter_5": "gillc102",
    "home_position_5": "8",
    "home_batter_6": "joose101",
    "home_position_6": "4",
    "home_batter_7": "masip101",
    "home_position_7": "2",
    "home_batter_8": "shems101",
    "home_position_8": "5",
    "home_batter_9": "javea101",
    "home_position_9": "1",
    "field83": "adama101",
    "field84": "cozac101"
  },
  {
    "game_id": "BSN194504180",
    "date": "19450418",
    "game_number": "0",
    "day_of_week": "Wednesday",
    "start_time": "0",
    "DH_used_flag": "F",
    "day_night_flag": "D",
    "visiting_team": "NY1",
    "home_team": "BSN",
    "game_site": "BOS08",
    "vis_starting_pitcher": "mungv101",
    "home_starting_pitcher": "andrn101",
    "home_plate_umpire": "stewb901",
    "first_base_umpire": "dunnt901",
    "second_base_umpire": "henlb101",
    "third_base_umpire": "mageg901",
    "left_field_umpire": "",
    "right_field_umpire": "",
    "attendance": "3007",
    "PS_scorer": "32",
    "translator": "Comly",
    "inputter": "Comly",
    "input_time": "2000/01/01 6:33PM",
    "edit_time": "",
    "how_scored": "1",
    "pitches_entered": "0",
    "temperature": "0",
    "wind_direction": "0",
    "wind_speed": "-1",
    "field_condition": "0",
    "precipitation": "0",
    "sky": "0",
    "time_of_game": "0",
    "number_of_innings": "9",
    "visitor_final_score": "8",
    "home_final_score": "4",
    "visitor_hits": "10",
    "home_hits": "10",
    "visitor_errors": "1",
    "home_errors": "1",
    "visitor_left_on_base": "11",
    "home_left_on_base": "9",
    "winning_pitcher": "adama101",
    "losing_pitcher": "andrn101",
    "save_for": "",
    "GW_RBI": "",
    "visitor_batter_1": "ruckj101",
    "visitor_position_1": "8",
    "visitor_batter_2": "hausg101",
    "visitor_position_2": "4",
    "visitor_batter_3": "ott-m101",
    "visitor_position_3": "9",
    "visitor_batter_4": "filis101",
    "visitor_position_4": "7",
    "visitor_batter_5": "weinp101",
    "visitor_position_5": "3",
    "visitor_batter_6": "lombe101",
    "visitor_position_6": "2",
    "visitor_batter_7": "kerrb101",
    "visitor_position_7": "6",
    "visitor_batter_8": "reyen101",
    "visitor_position_8": "5",
    "visitor_batter_9": "mungv101",
    "visitor_position_9": "1",
    "home_batter_1": "culld101",
    "home_position_1": "6",
    "home_batter_2": "holmt101",
    "home_position_2": "7",
    "home_batter_3": "workc101",
    "home_position_3": "9",
    "home_batter_4": "mackj101",
    "home_position_4": "3",
    "home_batter_5": "gillc102",
    "home_position_5": "8",
    "home_batter_6": "joose101",
    "home_position_6": "4",
    "home_batter_7": "klutc101",
    "home_position_7": "2",
    "home_batter_8": "shems101",
    "home_position_8": "5",
    "home_batter_9": "andrn101",
    "home_position_9": "1",
    "field83": "adama101",
    "field84": "cardb101"
  },
  {
    "game_id": "BSN194504191",
    "date": "19450419",
    "game_number": "1",
    "day_of_week": "Thursday",
    "start_time": "0",
    "DH_used_flag": "F",
    "day_night_flag": "D",
    "visiting_team": "NY1",
    "home_team": "BSN",
    "game_site": "BOS08",
    "vis_starting_pitcher": "hansa101",
    "home_starting_pitcher": "barrr101",
    "home_plate_umpire": "dunnt901",
    "first_base_umpire": "henlb101",
    "second_base_umpire": "mageg901",
    "third_base_umpire": "stewb901",
    "left_field_umpire": "",
    "right_field_umpire": "",
    "attendance": "1793",
    "PS_scorer": "32",
    "translator": "Comly",
    "inputter": "Comly",
    "input_time": "2000/01/01 6:46PM",
    "edit_time": "",
    "how_scored": "1",
    "pitches_entered": "0",
    "temperature": "0",
    "wind_direction": "0",
    "wind_speed": "-1",
    "field_condition": "0",
    "precipitation": "0",
    "sky": "0",
    "time_of_game": "0",
    "number_of_innings": "9",
    "visitor_final_score": "4",
    "home_final_score": "3",
    "visitor_hits": "8",
    "home_hits": "7",
    "visitor_errors": "1",
    "home_errors": "0",
    "visitor_left_on_base": "8",
    "home_left_on_base": "9",
    "winning_pitcher": "hansa101",
    "losing_pitcher": "barrr101",
    "save_for": "gee-j101",
    "GW_RBI": "",
    "visitor_batter_1": "ruckj101",
    "visitor_position_1": "8",
    "visitor_batter_2": "hausg101",
    "visitor_position_2": "4",
    "visitor_batter_3": "ott-m101",
    "visitor_position_3": "9",
    "visitor_batter_4": "filis101",
    "visitor_position_4": "7",
    "visitor_batter_5": "weinp101",
    "visitor_position_5": "3",
    "visitor_batter_6": "lombe101",
    "visitor_position_6": "2",
    "visitor_batter_7": "kerrb101",
    "visitor_position_7": "6",
    "visitor_batter_8": "reyen101",
    "visitor_position_8": "5",
    "visitor_batter_9": "hansa101",
    "visitor_position_9": "1",
    "home_batter_1": "culld101",
    "home_position_1": "6",
    "home_batter_2": "holmt101",
    "home_position_2": "7",
    "home_batter_3": "niemb102",
    "home_position_3": "9",
    "home_batter_4": "mackj101",
    "home_position_4": "3",
    "home_batter_5": "gillc102",
    "home_position_5": "8",
    "home_batter_6": "workc101",
    "home_position_6": "5",
    "home_batter_7": "masip101",
    "home_position_7": "2",
    "home_batter_8": "shems101",
    "home_position_8": "4",
    "home_batter_9": "barrr101",
    "home_position_9": "1",
    "field83": "gee-j101",
    "field84": ""
  },
  {
    "game_id": "BSN194504192",
    "date": "19450419",
    "game_number": "2",
    "day_of_week": "Thursday",
    "start_time": "0",
    "DH_used_flag": "F",
    "day_night_flag": "D",
    "visiting_team": "NY1",
    "home_team": "BSN",
    "game_site": "BOS08",
    "vis_starting_pitcher": "pylee101",
    "home_starting_pitcher": "tobij103",
    "home_plate_umpire": "henlb101",
    "first_base_umpire": "mageg901",
    "second_base_umpire": "stewb901",
    "third_base_umpire": "dunnt901",
    "left_field_umpire": "",
    "right_field_umpire": "",
    "attendance": "5506",
    "PS_scorer": "32",
    "translator": "Comly",
    "inputter": "Comly",
    "input_time": "2000/01/01 7:05PM",
    "edit_time": "",
    "how_scored": "1",
    "pitches_entered": "0",
    "temperature": "0",
    "wind_direction": "0",
    "wind_speed": "-1",
    "field_condition": "0",
    "precipitation": "0",
    "sky": "0",
    "time_of_game": "0",
    "number_of_innings": "9",
    "visitor_final_score": "5",
    "home_final_score": "13",
    "visitor_hits": "7",
    "home_hits": "15",
    "visitor_errors": "2",
    "home_errors": "0",
    "visitor_left_on_base": "7",
    "home_left_on_base": "9",
    "winning_pitcher": "tobij103",
    "losing_pitcher": "brewj101",
    "save_for": "",
    "GW_RBI": "",
    "visitor_batter_1": "ruckj101",
    "visitor_position_1": "8",
    "visitor_batter_2": "hausg101",
    "visitor_position_2": "4",
    "visitor_batter_3": "ott-m101",
    "visitor_position_3": "9",
    "visitor_batter_4": "filis101",
    "visitor_position_4": "7",
    "visitor_batter_5": "weinp101",
    "visitor_position_5": "3",
    "visitor_batter_6": "lombe101",
    "visitor_position_6": "2",
    "visitor_batter_7": "kerrb101",
    "visitor_position_7": "6",
    "visitor_batter_8": "reyen101",
    "visitor_position_8": "5",
    "visitor_batter_9": "pylee101",
    "visitor_position_9": "1",
    "home_batter_1": "culld101",
    "home_position_1": "6",
    "home_batter_2": "holmt101",
    "home_position_2": "7",
    "home_batter_3": "niemb102",
    "home_position_3": "9",
    "home_batter_4": "mackj101",
    "home_position_4": "3",
    "home_batter_5": "gillc102",
    "home_position_5": "8",
    "home_batter_6": "workc101",
    "home_position_6": "5",
    "home_batter_7": "masip101",
    "home_position_7": "2",
    "home_batter_8": "shems101",
    "home_position_8": "4",
    "home_batter_9": "tobij103",
    "home_position_9": "1",
    "field83": "harrr103",
    "field84": ""
  },
  {
    "game_id": "BSN194504240",
    "date": "19450424",
    "game_number": "0",
    "day_of_week": "Tuesday",
    "start_time": "0",
    "DH_used_flag": "F",
    "day_night_flag": "D",
    "visiting_team": "BRO",
    "home_team": "BSN",
    "game_site": "BOS08",
    "vis_starting_pitcher": "gregh102",
    "home_starting_pitcher": "tobij103",
    "home_plate_umpire": "pineb101",
    "first_base_umpire": "balll901",
    "second_base_umpire": "(none)",
    "third_base_umpire": "boggd901",
    "left_field_umpire": "",
    "right_field_umpire": "",
    "attendance": "1705",
    "PS_scorer": "38",
    "translator": "Comly",
    "inputter": "Comly",
    "input_time": "2000/04/01 10:13PM",
    "edit_time": "",
    "how_scored": "1",
    "pitches_entered": "0",
    "temperature": "0",
    "wind_direction": "0",
    "wind_speed": "-1",
    "field_condition": "0",
    "precipitation": "0",
    "sky": "0",
    "time_of_game": "152",
    "number_of_innings": "9",
    "visitor_final_score": "6",
    "home_final_score": "8",
    "visitor_hits": "10",
    "home_hits": "11",
    "visitor_errors": "1",
    "home_errors": "2",
    "visitor_left_on_base": "6",
    "home_left_on_base": "6",
    "winning_pitcher": "tobij103",
    "losing_pitcher": "gregh102",
    "save_for": "",
    "GW_RBI": "",
    "visitor_batter_1": "stane101",
    "visitor_position_1": "4",
    "visitor_batter_2": "sukec101",
    "visitor_position_2": "2",
    "visitor_batter_3": "galaa101",
    "visitor_position_3": "3",
    "visitor_batter_4": "walkd101",
    "visitor_position_4": "9",
    "visitor_batter_5": "aderm101",
    "visitor_position_5": "7",
    "visitor_batter_6": "durrr101",
    "visitor_position_6": "8",
    "visitor_batter_7": "hartb101",
    "visitor_position_7": "5",
    "visitor_batter_8": "basie101",
    "visitor_position_8": "6",
    "visitor_batter_9": "gregh102",
    "visitor_position_9": "1",
    "home_batter_1": "culld101",
    "home_position_1": "6",
    "home_batter_2": "holmt101",
    "home_position_2": "7",
    "home_batter_3": "niemb102",
    "home_position_3": "9",
    "home_batter_4": "mackj101",
    "home_position_4": "3",
    "home_batter_5": "gillc102",
    "home_position_5": "8",
    "home_batter_6": "walln101",
    "home_position_6": "5",
    "home_batter_7": "masip101",
    "home_position_7": "2",
    "home_batter_8": "shems101",
    "home_position_8": "4",
    "home_batter_9": "tobij103",
    "home_position_9": "1",
    "field83": "",
    "field84": ""
  },
  {
    "game_id": "BSN194504280",
    "date": "19450428",
    "game_number": "0",
    "day_of_week": "Saturday",
    "start_time": "0",
    "DH_used_flag": "F",
    "day_night_flag": "D",
    "visiting_team": "PHI",
    "home_team": "BSN",
    "game_site": "BOS08",
    "vis_starting_pitcher": "sproc101",
    "home_starting_pitcher": "barrr101",
    "home_plate_umpire": "balll901",
    "first_base_umpire": "boggd901",
    "second_base_umpire": "(none)",
    "third_base_umpire": "pineb101",
    "left_field_umpire": "",
    "right_field_umpire": "",
    "attendance": "2182",
    "PS_scorer": "115",
    "translator": "Bob Kistler",
    "inputter": "Greg Beston",
    "input_time": "2002/04/07 11:58AM",
    "edit_time": "",
    "how_scored": "0",
    "pitches_entered": "0",
    "temperature": "0",
    "wind_direction": "0",
    "wind_speed": "-1",
    "field_condition": "0",
    "precipitation": "0",
    "sky": "0",
    "time_of_game": "134",
    "number_of_innings": "9",
    "visitor_final_score": "7",
    "home_final_score": "8",
    "visitor_hits": "11",
    "home_hits": "10",
    "visitor_errors": "0",
    "home_errors": "2",
    "visitor_left_on_base": "8",
    "home_left_on_base": "9",
    "winning_pitcher": "earlt101",
    "losing_pitcher": "kennv101",
    "save_for": "hutcj101",
    "GW_RBI": "",
    "visitor_batter_1": "hamng101",
    "visitor_position_1": "4",
    "visitor_batter_2": "dingv101",
    "visitor_position_2": "9",
    "visitor_batter_3": "adamb101",
    "visitor_position_3": "7",
    "visitor_batter_4": "wasdj101",
    "visitor_position_4": "3",
    "visitor_batter_5": "dimav101",
    "visitor_position_5": "8",
    "visitor_batter_6": "foxxj101",
    "visitor_position_6": "5",
    "visitor_batter_7": "mancg101",
    "visitor_position_7": "2",
    "visitor_batter_8": "hamng102",
    "visitor_position_8": "6",
    "visitor_batter_9": "sproc101",
    "visitor_position_9": "1",
    "home_batter_1": "culld101",
    "home_position_1": "6",
    "home_batter_2": "holmt101",
    "home_position_2": "7",
    "home_batter_3": "niemb102",
    "home_position_3": "9",
    "home_batter_4": "mackj101",
    "home_position_4": "3",
    "home_batter_5": "gillc102",
    "home_position_5": "8",
    "home_batter_6": "masip101",
    "home_position_6": "2",
    "home_batter_7": "shems101",
    "home_position_7": "4",
    "home_batter_8": "wietw101",
    "home_position_8": "5",
    "home_batter_9": "barrr101",
    "home_position_9": "1",
    "field83": "karla101",
    "field84": "hutcj101"
  },
  {
    "game_id": "BSN194505090",
    "date": "19450509",
    "game_number": "0",
    "day_of_week": "Wednesday",
    "start_time": "0",
    "DH_used_flag": "F",
    "day_night_flag": "D",
    "visiting_team": "PIT",
    "home_team": "BSN",
    "game_site": "BOS08",
    "vis_starting_pitcher": "roe-p101",
    "home_starting_pitcher": "tobij103",
    "home_plate_umpire": "pineb101",
    "first_base_umpire": "balll901",
    "second_base_umpire": "(none)",
    "third_base_umpire": "boggd901",
    "left_field_umpire": "",
    "right_field_umpire": "",
    "attendance": "2574",
    "PS_scorer": "115",
    "translator": "Bob Kistler",
    "inputter": "Greg Beston",
    "input_time": "2002/04/07 1:21PM",
    "edit_time": "",
    "how_scored": "0",
    "pitches_entered": "0",
    "temperature": "0",
    "wind_direction": "0",
    "wind_speed": "-1",
    "field_condition": "0",
    "precipitation": "0",
    "sky": "0",
    "time_of_game": "130",
    "number_of_innings": "9",
    "visitor_final_score": "9",
    "home_final_score": "5",
    "visitor_hits": "13",
    "home_hits": "10",
    "visitor_errors": "0",
    "home_errors": "3",
    "visitor_left_on_base": "13",
    "home_left_on_base": "5",
    "winning_pitcher": "roe-p101",
    "losing_pitcher": "tobij103",
    "save_for": "rescx101",
    "GW_RBI": "",
    "visitor_batter_1": "coscp101",
    "visitor_position_1": "4",
    "visitor_batter_2": "barrj106",
    "visitor_position_2": "8",
    "visitor_batter_3": "obrit103",
    "visitor_position_3": "9",
    "visitor_batter_4": "ellib103",
    "visitor_position_4": "5",
    "visitor_batter_5": "russj102",
    "visitor_position_5": "7",
    "visitor_batter_6": "dahlb101",
    "visitor_position_6": "3",
    "visitor_batter_7": "gustf101",
    "visitor_position_7": "6",
    "visitor_batter_8": "lopea102",
    "visitor_position_8": "2",
    "visitor_batter_9": "roe-p101",
    "visitor_position_9": "1",
    "home_batter_1": "culld101",
    "home_position_1": "6",
    "home_batter_2": "holmt101",
    "home_position_2": "9",
    "home_batter_3": "niemb102",
    "home_position_3": "7",
    "home_batter_4": "mackj101",
    "home_position_4": "3",
    "home_batter_5": "gillc102",
    "home_position_5": "8",
    "home_batter_6": "workc101",
    "home_position_6": "5",
    "home_batter_7": "masip101",
    "home_position_7": "2",
    "home_batter_8": "wietw101",
    "home_position_8": "4",
    "home_batter_9": "tobij103",
    "home_position_9": "1",
    "field83": "rescx101",
    "field84": "schah103"
  },
  {
    "game_id": "BSN194505120",
    "date": "19450512",
    "game_number": "0",
    "day_of_week": "Saturday",
    "start_time": "0",
    "DH_used_flag": "F",
    "day_night_flag": "D",
    "visiting_team": "CHN",
    "home_team": "BSN",
    "game_site": "BOS08",
    "vis_starting_pitcher": "primr101",
    "home_starting_pitcher": "javea101",
    "home_plate_umpire": "balll901",
    "first_base_umpire": "boggd901",
    "second_base_umpire": "(none)",
    "third_base_umpire": "pineb101",
    "left_field_umpire": "",
    "right_field_umpire": "",
    "attendance": "3044",
    "PS_scorer": "115",
    "translator": "Bob Kistler",
    "inputter": "Greg Beston",
    "input_time": "2002/04/07 2:30PM",
    "edit_time": "",
    "how_scored": "0",
    "pitches_entered": "0",
    "temperature": "0",
    "wind_direction": "0",
    "wind_speed": "-1",
    "field_condition": "0",
    "precipitation": "0",
    "sky": "0",
    "time_of_game": "155",
    "number_of_innings": "9",
    "visitor_final_score": "13",
    "home_final_score": "12",
    "visitor_hits": "16",
    "home_hits": "14",
    "visitor_errors": "2",
    "home_errors": "1",
    "visitor_left_on_base": "10",
    "home_left_on_base": "8",
    "winning_pitcher": "wyseh101",
    "losing_pitcher": "barrr101",
    "save_for": "",
    "GW_RBI": "",
    "visitor_batter_1": "hacks101",
    "visitor_position_1": "5",
    "visitor_batter_2": "hughr101",
    "visitor_position_2": "6",
    "visitor_batter_3": "nichb101",
    "visitor_position_3": "9",
    "visitor_batter_4": "cavap101",
    "visitor_position_4": "3",
    "visitor_batter_5": "secof101",
    "visitor_position_5": "7",
    "visitor_batter_6": "lowrp101",
    "visitor_position_6": "8",
    "visitor_batter_7": "johnd101",
    "visitor_position_7": "4",
    "visitor_batter_8": "willd109",
    "visitor_position_8": "2",
    "visitor_batter_9": "primr101",
    "visitor_position_9": "1",
    "home_batter_1": "culld101",
    "home_position_1": "6",
    "home_batter_2": "holmt101",
    "home_position_2": "9",
    "home_batter_3": "niemb102",
    "home_position_3": "7",
    "home_batter_4": "mackj101",
    "home_position_4": "3",
    "home_batter_5": "gillc102",
    "home_position_5": "8",
    "home_batter_6": "workc101",
    "home_position_6": "5",
    "home_batter_7": "klutc101",
    "home_position_7": "2",
    "home_batter_8": "wietw101",
    "home_position_8": "4",
    "home_batter_9": "javea101",
    "home_position_9": "1",
    "field83": "wyseh101",
    "field84": "barrr101"
  },
  {
    "game_id": "BSN194505150",
    "date": "19450515",
    "game_number": "0",
    "day_of_week": "Tuesday",
    "start_time": "0",
    "DH_used_flag": "F",
    "day_night_flag": "D",
    "visiting_team": "SLN",
    "home_team": "BSN",
    "game_site": "BOS08",
    "vis_starting_pitcher": "parts101",
    "home_starting_pitcher": "barrr101",
    "home_plate_umpire": "mageg901",
    "first_base_umpire": "stewb901",
    "second_base_umpire": "(none)",
    "third_base_umpire": "dunnt901",
    "left_field_umpire": "",
    "right_field_umpire": "",
    "attendance": "2422",
    "PS_scorer": "115",
    "translator": "Bob Kistler",
    "inputter": "Greg Beston",
    "input_time": "2002/04/07 6:27PM",
    "edit_time": "",
    "how_scored": "0",
    "pitches_entered": "0",
    "temperature": "0",
    "wind_direction": "0",
    "wind_speed": "-1",
    "field_condition": "0",
    "precipitation": "0",
    "sky": "0",
    "time_of_game": "158",
    "number_of_innings": "9",
    "visitor_final_score": "8",
    "home_final_score": "7",
    "visitor_hits": "11",
    "home_hits": "13",
    "visitor_errors": "0",
    "home_errors": "2",
    "visitor_left_on_base": "10",
    "home_left_on_base": "12",
    "winning_pitcher": "creej101",
    "losing_pitcher": "schah103",
    "save_for": "donnb101",
    "GW_RBI": "",
    "visitor_batter_1": "berga102",
    "visitor_position_1": "9",
    "visitor_batter_2": "hoppj102",
    "visitor_position_2": "8",
    "visitor_batter_3": "adamb101",
    "visitor_position_3": "7",
    "visitor_batter_4": "sandr102",
    "visitor_position_4": "3",
    "visitor_batter_5": "kurow101",
    "visitor_position_5": "5",
    "visitor_batter_6": "odeak101",
    "visitor_position_6": "2",
    "visitor_batter_7": "verbe101",
    "visitor_position_7": "4",
    "visitor_batter_8": "fallg101",
    "visitor_position_8": "6",
    "visitor_batter_9": "parts101",
    "visitor_position_9": "1",
    "home_batter_1": "culld101",
    "home_position_1": "6",
    "home_batter_2": "holmt101",
    "home_position_2": "9",
    "home_batter_3": "niemb102",
    "home_position_3": "7",
    "home_batter_4": "mackj101",
    "home_position_4": "3",
    "home_batter_5": "gillc102",
    "home_position_5": "8",
    "home_batter_6": "workc101",
    "home_position_6": "5",
    "home_batter_7": "masip101",
    "home_position_7": "2",
    "home_batter_8": "wietw101",
    "home_position_8": "4",
    "home_batter_9": "barrr101",
    "home_position_9": "1",
    "field83": "donnb101",
    "field84": "schah103"
  },
  {
    "game_id": "BSN194505161",
    "date": "19450516",
    "game_number": "1",
    "day_of_week": "Wednesday",
    "start_time": "0",
    "DH_used_flag": "F",
    "day_night_flag": "D",
    "visiting_team": "SLN",
    "home_team": "BSN",
    "game_site": "BOS08",
    "vis_starting_pitcher": "byerb103",
    "home_starting_pitcher": "tobij103",
    "home_plate_umpire": "stewb901",
    "first_base_umpire": "dunnt901",
    "second_base_umpire": "(none)",
    "third_base_umpire": "mageg901",
    "left_field_umpire": "",
    "right_field_umpire": "",
    "attendance": "0",
    "PS_scorer": "115",
    "translator": "Bob Kistler",
    "inputter": "Greg Beston",
    "input_time": "2002/04/07 6:52PM",
    "edit_time": "",
    "how_scored": "0",
    "pitches_entered": "0",
    "temperature": "0",
    "wind_direction": "0",
    "wind_speed": "-1",
    "field_condition": "0",
    "precipitation": "0",
    "sky": "0",
    "time_of_game": "174",
    "number_of_innings": "14",
    "visitor_final_score": "4",
    "home_final_score": "5",
    "visitor_hits": "12",
    "home_hits": "7",
    "visitor_errors": "4",
    "home_errors": "3",
    "visitor_left_on_base": "12",
    "home_left_on_base": "9",
    "winning_pitcher": "barrr101",
    "losing_pitcher": "donnb101",
    "save_for": "",
    "GW_RBI": "",
    "visitor_batter_1": "berga102",
    "visitor_position_1": "9",
    "visitor_batter_2": "hoppj102",
    "visitor_position_2": "8",
    "visitor_batter_3": "adamb101",
    "visitor_position_3": "7",
    "visitor_batter_4": "sandr102",
    "visitor_position_4": "3",
    "visitor_batter_5": "kurow101",
    "visitor_position_5": "5",
    "visitor_batter_6": "odeak101",
    "visitor_position_6": "2",
    "visitor_batter_7": "verbe101",
    "visitor_position_7": "4",
    "visitor_batter_8": "marim101",
    "visitor_position_8": "6",
    "visitor_batter_9": "byerb103",
    "visitor_position_9": "1",
    "home_batter_1": "culld101",
    "home_position_1": "6",
    "home_batter_2": "holmt101",
    "home_position_2": "9",
    "home_batter_3": "niemb102",
    "home_position_3": "7",
    "home_batter_4": "mackj101",
    "home_position_4": "3",
    "home_batter_5": "workc101",
    "home_position_5": "5",
    "home_batter_6": "gillc102",
    "home_position_6": "8",
    "home_batter_7": "masip101",
    "home_position_7": "2",
    "home_batter_8": "wietw101",
    "home_position_8": "4",
    "home_batter_9": "tobij103",
    "home_position_9": "1",
    "field83": "donnb101",
    "field84": "barrr101"
  },
  {
    "game_id": "BSN194505170",
    "date": "19450517",
    "game_number": "0",
    "day_of_week": "Thursday",
    "start_time": "0",
    "DH_used_flag": "F",
    "day_night_flag": "D",
    "visiting_team": "SLN",
    "home_team": "BSN",
    "game_site": "BOS08",
    "vis_starting_pitcher": "parts101",
    "home_starting_pitcher": "andrn101",
    "home_plate_umpire": "mageg901",
    "first_base_umpire": "stewb901",
    "second_base_umpire": "(none)",
    "third_base_umpire": "dunnt901",
    "left_field_umpire": "",
    "right_field_umpire": "",
    "attendance": "685",
    "PS_scorer": "115",
    "translator": "Bob Kistler",
    "inputter": "Greg Beston",
    "input_time": "2002/04/07 7:12PM",
    "edit_time": "",
    "how_scored": "0",
    "pitches_entered": "0",
    "temperature": "0",
    "wind_direction": "0",
    "wind_speed": "-1",
    "field_condition": "0",
    "precipitation": "0",
    "sky": "3",
    "time_of_game": "132",
    "number_of_innings": "9",
    "visitor_final_score": "7",
    "home_final_score": "4",
    "visitor_hits": "11",
    "home_hits": "7",
    "visitor_errors": "0",
    "home_errors": "1",
    "visitor_left_on_base": "7",
    "home_left_on_base": "6",
    "winning_pitcher": "burkk101",
    "losing_pitcher": "andrn101",
    "save_for": "",
    "GW_RBI": "",
    "visitor_batter_1": "garmd101",
    "visitor_position_1": "9",
    "visitor_batter_2": "hoppj102",
    "visitor_position_2": "8",
    "visitor_batter_3": "adamb101",
    "visitor_position_3": "7",
    "visitor_batter_4": "sandr102",
    "visitor_position_4": "3",
    "visitor_batter_5": "kurow101",
    "visitor_position_5": "5",
    "visitor_batter_6": "odeak101",
    "visitor_position_6": "2",
    "visitor_batter_7": "verbe101",
    "visitor_position_7": "4",
    "visitor_batter_8": "marim101",
    "visitor_position_8": "6",
    "visitor_batter_9": "parts101",
    "visitor_position_9": "1",
    "home_batter_1": "culld101",
    "home_position_1": "6",
    "home_batter_2": "holmt101",
    "home_position_2": "9",
    "home_batter_3": "niemb102",
    "home_position_3": "7",
    "home_batter_4": "mackj101",
    "home_position_4": "3",
    "home_batter_5": "gillc102",
    "home_position_5": "8",
    "home_batter_6": "workc101",
    "home_position_6": "5",
    "home_batter_7": "klutc101",
    "home_position_7": "2",
    "home_batter_8": "joose101",
    "home_position_8": "4",
    "home_batter_9": "andrn101",
    "home_position_9": "1",
    "field83": "burkk101",
    "field84": "schah103"
  },
  {
    "game_id": "BSN194506090",
    "date": "19450609",
    "game_number": "0",
    "day_of_week": "Saturday",
    "start_time": "0",
    "DH_used_flag": "F",
    "day_night_flag": "D",
    "visiting_team": "NY1",
    "home_team": "BSN",
    "game_site": "BOS08",
    "vis_starting_pitcher": "feldh101",
    "home_starting_pitcher": "logab101",
    "home_plate_umpire": "barrg901",
    "first_base_umpire": "dunnt901",
    "second_base_umpire": "(none)",
    "third_base_umpire": "searz901",
    "left_field_umpire": "",
    "right_field_umpire": "",
    "attendance": "5082",
    "PS_scorer": "32",
    "translator": "Comly",
    "inputter": "Comly",
    "input_time": "2000/01/09 12:13PM",
    "edit_time": "",
    "how_scored": "1",
    "pitches_entered": "0",
    "temperature": "0",
    "wind_direction": "0",
    "wind_speed": "-1",
    "field_condition": "0",
    "precipitation": "0",
    "sky": "0",
    "time_of_game": "0",
    "number_of_innings": "9",
    "visitor_final_score": "0",
    "home_final_score": "4",
    "visitor_hits": "7",
    "home_hits": "9",
    "visitor_errors": "2",
    "home_errors": "3",
    "visitor_left_on_base": "9",
    "home_left_on_base": "8",
    "winning_pitcher": "logab101",
    "losing_pitcher": "feldh101",
    "save_for": "",
    "GW_RBI": "",
    "visitor_batter_1": "ruckj101",
    "visitor_position_1": "8",
    "visitor_batter_2": "hausg101",
    "visitor_position_2": "4",
    "visitor_batter_3": "ott-m101",
    "visitor_position_3": "9",
    "visitor_batter_4": "medwj101",
    "visitor_position_4": "7",
    "visitor_batter_5": "lombe101",
    "visitor_position_5": "2",
    "visitor_batter_6": "jurgb101",
    "visitor_position_6": "5",
    "visitor_batter_7": "kerrb101",
    "visitor_position_7": "6",
    "visitor_batter_8": "garda104",
    "visitor_position_8": "3",
    "visitor_batter_9": "feldh101",
    "visitor_position_9": "1",
    "home_batter_1": "joose101",
    "home_position_1": "5",
    "home_batter_2": "holmt101",
    "home_position_2": "7",
    "home_batter_3": "mackj101",
    "home_position_3": "3",
    "home_batter_4": "workc101",
    "home_position_4": "9",
    "home_batter_5": "gillc102",
    "home_position_5": "8",
    "home_batter_6": "masip101",
    "home_position_6": "2",
    "home_batter_7": "drewf101",
    "home_position_7": "4",
    "home_batter_8": "wietw101",
    "home_position_8": "6",
    "home_batter_9": "logab101",
    "home_position_9": "1",
    "field83": "adama101",
    "field84": ""
  },
  {
    "game_id": "BSN194506101",
    "date": "19450610",
    "game_number": "1",
    "day_of_week": "Sunday",
    "start_time": "0",
    "DH_used_flag": "F",
    "day_night_flag": "D",
    "visiting_team": "NY1",
    "home_team": "BSN",
    "game_site": "BOS08",
    "vis_starting_pitcher": "voisb101",
    "home_starting_pitcher": "coopm101",
    "home_plate_umpire": "dunnt901",
    "first_base_umpire": "searz901",
    "second_base_umpire": "(none)",
    "third_base_umpire": "barrg901",
    "left_field_umpire": "",
    "right_field_umpire": "",
    "attendance": "0",
    "PS_scorer": "32",
    "translator": "Comly",
    "inputter": "Comly",
    "input_time": "2000/01/09 12:34PM",
    "edit_time": "",
    "how_scored": "1",
    "pitches_entered": "0",
    "temperature": "0",
    "wind_direction": "0",
    "wind_speed": "-1",
    "field_condition": "0",
    "precipitation": "0",
    "sky": "0",
    "time_of_game": "0",
    "number_of_innings": "9",
    "visitor_final_score": "5",
    "home_final_score": "8",
    "visitor_hits": "13",
    "home_hits": "9",
    "visitor_errors": "1",
    "home_errors": "2",
    "visitor_left_on_base": "9",
    "home_left_on_base": "4",
    "winning_pitcher": "coopm101",
    "losing_pitcher": "voisb101",
    "save_for": "",
    "GW_RBI": "",
    "visitor_batter_1": "ruckj101",
    "visitor_position_1": "8",
    "visitor_batter_2": "hausg101",
    "visitor_position_2": "4",
    "visitor_batter_3": "ott-m101",
    "visitor_position_3": "9",
    "visitor_batter_4": "medwj101",
    "visitor_position_4": "7",
    "visitor_batter_5": "lombe101",
    "visitor_position_5": "2",
    "visitor_batter_6": "gardd101",
    "visitor_position_6": "3",
    "visitor_batter_7": "jurgb101",
    "visitor_position_7": "5",
    "visitor_batter_8": "kerrb101",
    "visitor_position_8": "6",
    "visitor_batter_9": "voisb101",
    "visitor_position_9": "1",
    "home_batter_1": "joose101",
    "home_position_1": "5",
    "home_batter_2": "holmt101",
    "home_position_2": "7",
    "home_batter_3": "mackj101",
    "home_position_3": "3",
    "home_batter_4": "workc101",
    "home_position_4": "9",
    "home_batter_5": "gillc102",
    "home_position_5": "8",
    "home_batter_6": "klutc101",
    "home_position_6": "2",
    "home_batter_7": "drewf101",
    "home_position_7": "4",
    "home_batter_8": "wietw101",
    "home_position_8": "6",
    "home_batter_9": "coopm101",
    "home_position_9": "1",
    "field83": "emmes101",
    "field84": ""
  },
  {
    "game_id": "BSN194506102",
    "date": "19450610",
    "game_number": "2",
    "day_of_week": "Sunday",
    "start_time": "0",
    "DH_used_flag": "F",
    "day_night_flag": "D",
    "visiting_team": "NY1",
    "home_team": "BSN",
    "game_site": "BOS08",
    "vis_starting_pitcher": "hansa101",
    "home_starting_pitcher": "tobij103",
    "home_plate_umpire": "searz901",
    "first_base_umpire": "barrg901",
    "second_base_umpire": "(none)",
    "third_base_umpire": "dunnt901",
    "left_field_umpire": "",
    "right_field_umpire": "",
    "attendance": "27835",
    "PS_scorer": "32",
    "translator": "Comly",
    "inputter": "Comly",
    "input_time": "2000/01/09 3:50PM",
    "edit_time": "",
    "how_scored": "1",
    "pitches_entered": "0",
    "temperature": "0",
    "wind_direction": "0",
    "wind_speed": "-1",
    "field_condition": "0",
    "precipitation": "0",
    "sky": "0",
    "time_of_game": "0",
    "number_of_innings": "9",
    "visitor_final_score": "1",
    "home_final_score": "3",
    "visitor_hits": "5",
    "home_hits": "7",
    "visitor_errors": "0",
    "home_errors": "2",
    "visitor_left_on_base": "8",
    "home_left_on_base": "5",
    "winning_pitcher": "tobij103",
    "losing_pitcher": "hansa101",
    "save_for": "",
    "GW_RBI": "",
    "visitor_batter_1": "ruckj101",
    "visitor_position_1": "8",
    "visitor_batter_2": "hausg101",
    "visitor_position_2": "4",
    "visitor_batter_3": "ott-m101",
    "visitor_position_3": "9",
    "visitor_batter_4": "medwj101",
    "visitor_position_4": "7",
    "visitor_batter_5": "lombe101",
    "visitor_position_5": "2",
    "visitor_batter_6": "gardd101",
    "visitor_position_6": "3",
    "visitor_batter_7": "jurgb101",
    "visitor_position_7": "5",
    "visitor_batter_8": "kerrb101",
    "visitor_position_8": "6",
    "visitor_batter_9": "hansa101",
    "visitor_position_9": "1",
    "home_batter_1": "culld101",
    "home_position_1": "5",
    "home_batter_2": "holmt101",
    "home_position_2": "7",
    "home_batter_3": "mackj101",
    "home_position_3": "3",
    "home_batter_4": "workc101",
    "home_position_4": "9",
    "home_batter_5": "gillc102",
    "home_position_5": "8",
    "home_batter_6": "masip101",
    "home_position_6": "2",
    "home_batter_7": "drewf101",
    "home_position_7": "4",
    "home_batter_8": "wietw101",
    "home_position_8": "6",
    "home_batter_9": "tobij103",
    "home_position_9": "1",
    "field83": "fiscr101",
    "field84": ""
  },
  {
    "game_id": "BSN194506131",
    "date": "19450613",
    "game_number": "1",
    "day_of_week": "Wednesday",
    "start_time": "0",
    "DH_used_flag": "F",
    "day_night_flag": "D",
    "visiting_team": "PHI",
    "home_team": "BSN",
    "game_site": "BOS08",
    "vis_starting_pitcher": "barrd101",
    "home_starting_pitcher": "coopm101",
    "home_plate_umpire": "dunnt901",
    "first_base_umpire": "searz901",
    "second_base_umpire": "(none)",
    "third_base_umpire": "barrg901",
    "left_field_umpire": "",
    "right_field_umpire": "",
    "attendance": "0",
    "PS_scorer": "115",
    "translator": "Bob Kistler",
    "inputter": "Greg Beston",
    "input_time": "2002/05/07 7:11PM",
    "edit_time": "",
    "how_scored": "0",
    "pitches_entered": "0",
    "temperature": "0",
    "wind_direction": "0",
    "wind_speed": "-1",
    "field_condition": "0",
    "precipitation": "0",
    "sky": "0",
    "time_of_game": "111",
    "number_of_innings": "9",
    "visitor_final_score": "3",
    "home_final_score": "8",
    "visitor_hits": "6",
    "home_hits": "10",
    "visitor_errors": "3",
    "home_errors": "2",
    "visitor_left_on_base": "5",
    "home_left_on_base": "5",
    "winning_pitcher": "coopm101",
    "losing_pitcher": "barrd101",
    "save_for": "",
    "GW_RBI": "",
    "visitor_batter_1": "flagw101",
    "visitor_position_1": "6",
    "visitor_batter_2": "antoj101",
    "visitor_position_2": "5",
    "visitor_batter_3": "wasdj101",
    "visitor_position_3": "3",
    "visitor_batter_4": "crawg101",
    "visitor_position_4": "7",
    "visitor_batter_5": "montr101",
    "visitor_position_5": "9",
    "visitor_batter_6": "dingv101",
    "visitor_position_6": "8",
    "visitor_batter_7": "peacj101",
    "visitor_position_7": "2",
    "visitor_batter_8": "danit101",
    "visitor_position_8": "4",
    "visitor_batter_9": "barrd101",
    "visitor_position_9": "1",
    "home_batter_1": "culld101",
    "home_position_1": "5",
    "home_batter_2": "holmt101",
    "home_position_2": "7",
    "home_batter_3": "mackj101",
    "home_position_3": "3",
    "home_batter_4": "workc101",
    "home_position_4": "9",
    "home_batter_5": "gillc102",
    "home_position_5": "8",
    "home_batter_6": "masip101",
    "home_position_6": "2",
    "home_batter_7": "drewf101",
    "home_position_7": "4",
    "home_batter_8": "wietw101",
    "home_position_8": "6",
    "home_batter_9": "coopm101",
    "home_position_9": "1",
    "field83": "lucil101",
    "field84": ""
  },
  {
    "game_id": "BSN194506150",
    "date": "19450615",
    "game_number": "0",
    "day_of_week": "Friday",
    "start_time": "0",
    "DH_used_flag": "F",
    "day_night_flag": "D",
    "visiting_team": "BRO",
    "home_team": "BSN",
    "game_site": "BOS08",
    "vis_starting_pitcher": "pfunl101",
    "home_starting_pitcher": "tobij103",
    "home_plate_umpire": "henlb101",
    "first_base_umpire": "goetl901",
    "second_base_umpire": "(none)",
    "third_base_umpire": "jordl901",
    "left_field_umpire": "",
    "right_field_umpire": "",
    "attendance": "5368",
    "PS_scorer": "38",
    "translator": "Comly",
    "inputter": "Comly",
    "input_time": "2000/05/01 11:21PM",
    "edit_time": "",
    "how_scored": "1",
    "pitches_entered": "0",
    "temperature": "0",
    "wind_direction": "0",
    "wind_speed": "-1",
    "field_condition": "0",
    "precipitation": "0",
    "sky": "0",
    "time_of_game": "134",
    "number_of_innings": "9",
    "visitor_final_score": "9",
    "home_final_score": "8",
    "visitor_hits": "16",
    "home_hits": "8",
    "visitor_errors": "2",
    "home_errors": "1",
    "visitor_left_on_base": "10",
    "home_left_on_base": "1",
    "winning_pitcher": "kingc101",
    "losing_pitcher": "hutci101",
    "save_for": "",
    "GW_RBI": "",
    "visitor_batter_1": "stane101",
    "visitor_position_1": "4",
    "visitor_batter_2": "roseg101",
    "visitor_position_2": "8",
    "visitor_batter_3": "galaa101",
    "visitor_position_3": "7",
    "visitor_batter_4": "walkd101",
    "visitor_position_4": "9",
    "visitor_batter_5": "olmol101",
    "visitor_position_5": "5",
    "visitor_batter_6": "schuh101",
    "visitor_position_6": "3",
    "visitor_batter_7": "dantf101",
    "visitor_position_7": "2",
    "visitor_batter_8": "basie101",
    "visitor_position_8": "6",
    "visitor_batter_9": "pfunl101",
    "visitor_position_9": "1",
    "home_batter_1": "culld101",
    "home_position_1": "5",
    "home_batter_2": "holmt101",
    "home_position_2": "7",
    "home_batter_3": "mackj101",
    "home_position_3": "3",
    "home_batter_4": "workc101",
    "home_position_4": "9",
    "home_batter_5": "gillc102",
    "home_position_5": "8",
    "home_batter_6": "masip101",
    "home_position_6": "2",
    "home_batter_7": "drewf101",
    "home_position_7": "4",
    "home_batter_8": "wietw101",
    "home_position_8": "6",
    "home_batter_9": "tobij103",
    "home_position_9": "1",
    "field83": "kingc101",
    "field84": "hutci101"
  },
  {
    "game_id": "BSN194506160",
    "date": "19450616",
    "game_number": "0",
    "day_of_week": "Saturday",
    "start_time": "0",
    "DH_used_flag": "F",
    "day_night_flag": "D",
    "visiting_team": "BRO",
    "home_team": "BSN",
    "game_site": "BOS08",
    "vis_starting_pitcher": "herra101",
    "home_starting_pitcher": "pylee101",
    "home_plate_umpire": "goetl901",
    "first_base_umpire": "jordl901",
    "second_base_umpire": "(none)",
    "third_base_umpire": "henlb101",
    "left_field_umpire": "",
    "right_field_umpire": "",
    "attendance": "2321",
    "PS_scorer": "38",
    "translator": "Comly",
    "inputter": "Comly",
    "input_time": "2000/05/01 11:49PM",
    "edit_time": "",
    "how_scored": "1",
    "pitches_entered": "0",
    "temperature": "0",
    "wind_direction": "0",
    "wind_speed": "-1",
    "field_condition": "0",
    "precipitation": "0",
    "sky": "0",
    "time_of_game": "215",
    "number_of_innings": "12",
    "visitor_final_score": "5",
    "home_final_score": "6",
    "visitor_hits": "12",
    "home_hits": "11",
    "visitor_errors": "3",
    "home_errors": "2",
    "visitor_left_on_base": "14",
    "home_left_on_base": "13",
    "winning_pitcher": "hutcj101",
    "losing_pitcher": "davic103",
    "save_for": "",
    "GW_RBI": "",
    "visitor_batter_1": "stane101",
    "visitor_position_1": "4",
    "visitor_batter_2": "roseg101",
    "visitor_position_2": "8",
    "visitor_batter_3": "galaa101",
    "visitor_position_3": "7",
    "visitor_batter_4": "walkd101",
    "visitor_position_4": "9",
    "visitor_batter_5": "olmol101",
    "visitor_position_5": "5",
    "visitor_batter_6": "schuh101",
    "visitor_position_6": "3",
    "visitor_batter_7": "dantf101",
    "visitor_position_7": "2",
    "visitor_batter_8": "basie101",
    "visitor_position_8": "6",
    "visitor_batter_9": "herra101",
    "visitor_position_9": "1",
    "home_batter_1": "culld101",
    "home_position_1": "6",
    "home_batter_2": "holmt101",
    "home_position_2": "9",
    "home_batter_3": "workc101",
    "home_position_3": "5",
    "home_batter_4": "medwj101",
    "home_position_4": "7",
    "home_batter_5": "gillc102",
    "home_position_5": "8",
    "home_batter_6": "mackj101",
    "home_position_6": "3",
    "home_batter_7": "masip101",
    "home_position_7": "2",
    "home_batter_8": "drewf101",
    "home_position_8": "4",
    "home_batter_9": "pylee101",
    "home_position_9": "1",
    "field83": "davic103",
    "field84": "hutcj101"
  },
  {
    "game_id": "BSN194506171",
    "date": "19450617",
    "game_number": "1",
    "day_of_week": "Sunday",
    "start_time": "0",
    "DH_used_flag": "F",
    "day_night_flag": "D",
    "visiting_team": "BRO",
    "home_team": "BSN",
    "game_site": "BOS08",
    "vis_starting_pitcher": "gregh102",
    "home_starting_pitcher": "coopm101",
    "home_plate_umpire": "jordl901",
    "first_base_umpire": "henlb101",
    "second_base_umpire": "(none)",
    "third_base_umpire": "goetl901",
    "left_field_umpire": "",
    "right_field_umpire": "",
    "attendance": "0",
    "PS_scorer": "38",
    "translator": "Comly",
    "inputter": "Comly",
    "input_time": "2000/05/03 9:57PM",
    "edit_time": "",
    "how_scored": "1",
    "pitches_entered": "0",
    "temperature": "0",
    "wind_direction": "0",
    "wind_speed": "-1",
    "field_condition": "0",
    "precipitation": "0",
    "sky": "0",
    "time_of_game": "168",
    "number_of_innings": "9",
    "visitor_final_score": "9",
    "home_final_score": "6",
    "visitor_hits": "14",
    "home_hits": "8",
    "visitor_errors": "1",
    "home_errors": "3",
    "visitor_left_on_base": "9",
    "home_left_on_base": "8",
    "winning_pitcher": "gregh102",
    "losing_pitcher": "coopm101",
    "save_for": "kingc101",
    "GW_RBI": "",
    "visitor_batter_1": "stane101",
    "visitor_position_1": "4",
    "visitor_batter_2": "roseg101",
    "visitor_position_2": "8",
    "visitor_batter_3": "galaa101",
    "visitor_position_3": "7",
    "visitor_batter_4": "walkd101",
    "visitor_position_4": "9",
    "visitor_batter_5": "olmol101",
    "visitor_position_5": "5",
    "visitor_batter_6": "schuh101",
    "visitor_position_6": "3",
    "visitor_batter_7": "basie101",
    "visitor_position_7": "6",
    "visitor_batter_8": "dantf101",
    "visitor_position_8": "2",
    "visitor_batter_9": "gregh102",
    "visitor_position_9": "1",
    "home_batter_1": "culld101",
    "home_position_1": "6",
    "home_batter_2": "holmt101",
    "home_position_2": "9",
    "home_batter_3": "workc101",
    "home_position_3": "5",
    "home_batter_4": "medwj101",
    "home_position_4": "7",
    "home_batter_5": "gillc102",
    "home_position_5": "8",
    "home_batter_6": "mackj101",
    "home_position_6": "3",
    "home_batter_7": "masip101",
    "home_position_7": "2",
    "home_batter_8": "drewf101",
    "home_position_8": "4",
    "home_batter_9": "coopm101",
    "home_position_9": "1",
    "field83": "kingc101",
    "field84": "fettl101"
  },
  {
    "game_id": "BSN194506172",
    "date": "19450617",
    "game_number": "2",
    "day_of_week": "Sunday",
    "start_time": "0",
    "DH_used_flag": "F",
    "day_night_flag": "D",
    "visiting_team": "BRO",
    "home_team": "BSN",
    "game_site": "BOS08",
    "vis_starting_pitcher": "lombv101",
    "home_starting_pitcher": "logab101",
    "home_plate_umpire": "henlb101",
    "first_base_umpire": "goetl901",
    "second_base_umpire": "(none)",
    "third_base_umpire": "jordl901",
    "left_field_umpire": "",
    "right_field_umpire": "",
    "attendance": "29231",
    "PS_scorer": "38",
    "translator": "Comly",
    "inputter": "Comly",
    "input_time": "2000/05/03 10:39PM",
    "edit_time": "",
    "how_scored": "1",
    "pitches_entered": "0",
    "temperature": "0",
    "wind_direction": "0",
    "wind_speed": "-1",
    "field_condition": "0",
    "precipitation": "0",
    "sky": "0",
    "time_of_game": "119",
    "number_of_innings": "9",
    "visitor_final_score": "1",
    "home_final_score": "4",
    "visitor_hits": "7",
    "home_hits": "5",
    "visitor_errors": "3",
    "home_errors": "0",
    "visitor_left_on_base": "7",
    "home_left_on_base": "5",
    "winning_pitcher": "logab101",
    "losing_pitcher": "lombv101",
    "save_for": "",
    "GW_RBI": "",
    "visitor_batter_1": "stane101",
    "visitor_position_1": "4",
    "visitor_batter_2": "roseg101",
    "visitor_position_2": "8",
    "visitor_batter_3": "galaa101",
    "visitor_position_3": "7",
    "visitor_batter_4": "walkd101",
    "visitor_position_4": "9",
    "visitor_batter_5": "olmol101",
    "visitor_position_5": "5",
    "visitor_batter_6": "schuh101",
    "visitor_position_6": "3",
    "visitor_batter_7": "basie101",
    "visitor_position_7": "6",
    "visitor_batter_8": "haywr101",
    "visitor_position_8": "2",
    "visitor_batter_9": "lombv101",
    "visitor_position_9": "1",
    "home_batter_1": "culld101",
    "home_position_1": "6",
    "home_batter_2": "holmt101",
    "home_position_2": "9",
    "home_batter_3": "workc101",
    "home_position_3": "5",
    "home_batter_4": "medwj101",
    "home_position_4": "7",
    "home_batter_5": "gillc102",
    "home_position_5": "8",
    "home_batter_6": "mackj101",
    "home_position_6": "3",
    "home_batter_7": "masip101",
    "home_position_7": "2",
    "home_batter_8": "drewf101",
    "home_position_8": "4",
    "home_batter_9": "logab101",
    "home_position_9": "1",
    "field83": "kingc101",
    "field84": ""
  },
  {
    "game_id": "BSN194506271",
    "date": "19450627",
    "game_number": "1",
    "day_of_week": "Wednesday",
    "start_time": "0",
    "DH_used_flag": "F",
    "day_night_flag": "D",
    "visiting_team": "CIN",
    "home_team": "BSN",
    "game_site": "BOS08",
    "vis_starting_pitcher": "kennv101",
    "home_starting_pitcher": "coopm101",
    "home_plate_umpire": "goetl901",
    "first_base_umpire": "jordl901",
    "second_base_umpire": "henlb101",
    "third_base_umpire": "rearb901",
    "left_field_umpire": "",
    "right_field_umpire": "",
    "attendance": "4524",
    "PS_scorer": "115",
    "translator": "Bob Kistler",
    "inputter": "Greg Beston",
    "input_time": "2002/05/10 6:42PM",
    "edit_time": "",
    "how_scored": "0",
    "pitches_entered": "0",
    "temperature": "0",
    "wind_direction": "0",
    "wind_speed": "-1",
    "field_condition": "0",
    "precipitation": "0",
    "sky": "0",
    "time_of_game": "138",
    "number_of_innings": "10",
    "visitor_final_score": "5",
    "home_final_score": "4",
    "visitor_hits": "11",
    "home_hits": "9",
    "visitor_errors": "1",
    "home_errors": "2",
    "visitor_left_on_base": "8",
    "home_left_on_base": "13",
    "winning_pitcher": "kennv101",
    "losing_pitcher": "hutci101",
    "save_for": "",
    "GW_RBI": "",
    "visitor_batter_1": "clayd101",
    "visitor_position_1": "8",
    "visitor_batter_2": "tipte101",
    "visitor_position_2": "7",
    "visitor_batter_3": "libka101",
    "visitor_position_3": "9",
    "visitor_batter_4": "mccof101",
    "visitor_position_4": "3",
    "visitor_batter_5": "mesns101",
    "visitor_position_5": "5",
    "visitor_batter_6": "mille104",
    "visitor_position_6": "6",
    "visitor_batter_7": "willw101",
    "visitor_position_7": "4",
    "visitor_batter_8": "unsea101",
    "visitor_position_8": "2",
    "visitor_batter_9": "kennv101",
    "visitor_position_9": "1",
    "home_batter_1": "culld101",
    "home_position_1": "6",
    "home_batter_2": "holmt101",
    "home_position_2": "9",
    "home_batter_3": "gillc102",
    "home_position_3": "8",
    "home_batter_4": "medwj101",
    "home_position_4": "7",
    "home_batter_5": "workc101",
    "home_position_5": "5",
    "home_batter_6": "masip101",
    "home_position_6": "2",
    "home_batter_7": "mackj101",
    "home_position_7": "3",
    "home_batter_8": "wietw101",
    "home_position_8": "4",
    "home_batter_9": "coopm101",
    "home_position_9": "1",
    "field83": "",
    "field84": "hutcj101"
  },
  {
    "game_id": "BSN194506300",
    "date": "19450630",
    "game_number": "0",
    "day_of_week": "Saturday",
    "start_time": "0",
    "DH_used_flag": "F",
    "day_night_flag": "D",
    "visiting_team": "SLN",
    "home_team": "BSN",
    "game_site": "BOS08",
    "vis_starting_pitcher": "creej101",
    "home_starting_pitcher": "pylee101",
    "home_plate_umpire": "goetl901",
    "first_base_umpire": "jordl901",
    "second_base_umpire": "henlb101",
    "third_base_umpire": "rearb901",
    "left_field_umpire": "",
    "right_field_umpire": "",
    "attendance": "3698",
    "PS_scorer": "115",
    "translator": "Bob Kistler",
    "inputter": "Greg Beston",
    "input_time": "2002/05/13 2:04PM",
    "edit_time": "",
    "how_scored": "0",
    "pitches_entered": "0",
    "temperature": "0",
    "wind_direction": "0",
    "wind_speed": "-1",
    "field_condition": "0",
    "precipitation": "0",
    "sky": "0",
    "time_of_game": "136",
    "number_of_innings": "9",
    "visitor_final_score": "4",
    "home_final_score": "8",
    "visitor_hits": "9",
    "home_hits": "11",
    "visitor_errors": "1",
    "home_errors": "1",
    "visitor_left_on_base": "9",
    "home_left_on_base": "6",
    "winning_pitcher": "hutcj101",
    "losing_pitcher": "creej101",
    "save_for": "",
    "GW_RBI": "",
    "visitor_batter_1": "bartd102",
    "visitor_position_1": "9",
    "visitor_batter_2": "schor101",
    "visitor_position_2": "7",
    "visitor_batter_3": "adamb101",
    "visitor_position_3": "8",
    "visitor_batter_4": "kurow101",
    "visitor_position_4": "5",
    "visitor_batter_5": "sandr102",
    "visitor_position_5": "3",
    "visitor_batter_6": "riced101",
    "visitor_position_6": "2",
    "visitor_batter_7": "verbe101",
    "visitor_position_7": "4",
    "visitor_batter_8": "marim101",
    "visitor_position_8": "6",
    "visitor_batter_9": "creej101",
    "visitor_position_9": "1",
    "home_batter_1": "culld101",
    "home_position_1": "6",
    "home_batter_2": "masip101",
    "home_position_2": "2",
    "home_batter_3": "holmt101",
    "home_position_3": "9",
    "home_batter_4": "medwj101",
    "home_position_4": "7",
    "home_batter_5": "workc101",
    "home_position_5": "5",
    "home_batter_6": "gillc102",
    "home_position_6": "8",
    "home_batter_7": "mackj101",
    "home_position_7": "3",
    "home_batter_8": "wietw101",
    "home_position_8": "4",
    "home_batter_9": "pylee101",
    "home_position_9": "1",
    "field83": "juria101",
    "field84": "hutcj101"
  },
  {
    "game_id": "BSN194507061",
    "date": "19450706",
    "game_number": "1",
    "day_of_week": "Friday",
    "start_time": "0",
    "DH_used_flag": "F",
    "day_night_flag": "D",
    "visiting_team": "PIT",
    "home_team": "BSN",
    "game_site": "BOS08",
    "vis_starting_pitcher": "gerha101",
    "home_starting_pitcher": "andrn101",
    "home_plate_umpire": "searz901",
    "first_base_umpire": "barrg901",
    "second_base_umpire": "(none)",
    "third_base_umpire": "dunnt901",
    "left_field_umpire": "",
    "right_field_umpire": "",
    "attendance": "0",
    "PS_scorer": "115",
    "translator": "Bob Kistler",
    "inputter": "Greg Beston",
    "input_time": "2002/05/13 2:54PM",
    "edit_time": "",
    "how_scored": "0",
    "pitches_entered": "0",
    "temperature": "0",
    "wind_direction": "0",
    "wind_speed": "-1",
    "field_condition": "0",
    "precipitation": "0",
    "sky": "0",
    "time_of_game": "129",
    "number_of_innings": "9",
    "visitor_final_score": "5",
    "home_final_score": "13",
    "visitor_hits": "9",
    "home_hits": "12",
    "visitor_errors": "3",
    "home_errors": "0",
    "visitor_left_on_base": "5",
    "home_left_on_base": "6",
    "winning_pitcher": "andrn101",
    "losing_pitcher": "rescx101",
    "save_for": "coopm101",
    "GW_RBI": "",
    "visitor_batter_1": "coscp101",
    "visitor_position_1": "4",
    "visitor_batter_2": "russj102",
    "visitor_position_2": "7",
    "visitor_batter_3": "giona101",
    "visitor_position_3": "8",
    "visitor_batter_4": "colmf101",
    "visitor_position_4": "3",
    "visitor_batter_5": "salkb101",
    "visitor_position_5": "2",
    "visitor_batter_6": "ellib103",
    "visitor_position_6": "5",
    "visitor_batter_7": "barrj106",
    "visitor_position_7": "9",
    "visitor_batter_8": "barnv102",
    "visitor_position_8": "6",
    "visitor_batter_9": "gerha101",
    "visitor_position_9": "1",
    "home_batter_1": "ramsb101",
    "home_position_1": "7",
    "home_batter_2": "culld101",
    "home_position_2": "6",
    "home_batter_3": "holmt101",
    "home_position_3": "9",
    "home_batter_4": "workc101",
    "home_position_4": "5",
    "home_batter_5": "masip101",
    "home_position_5": "3",
    "home_batter_6": "gillc102",
    "home_position_6": "8",
    "home_batter_7": "hoffs101",
    "home_position_7": "2",
    "home_batter_8": "drewf101",
    "home_position_8": "4",
    "home_batter_9": "andrn101",
    "home_position_9": "1",
    "field83": "rescx101",
    "field84": "coopm101"
  },
  {
    "game_id": "BSN194507070",
    "date": "19450707",
    "game_number": "0",
    "day_of_week": "Saturday",
    "start_time": "0",
    "DH_used_flag": "F",
    "day_night_flag": "D",
    "visiting_team": "PIT",
    "home_team": "BSN",
    "game_site": "BOS08",
    "vis_starting_pitcher": "sewer101",
    "home_starting_pitcher": "hutcj101",
    "home_plate_umpire": "dunnt901",
    "first_base_umpire": "searz901",
    "second_base_umpire": "(none)",
    "third_base_umpire": "barrg901",
    "left_field_umpire": "",
    "right_field_umpire": "",
    "attendance": "5159",
    "PS_scorer": "115",
    "translator": "Bob Kistler",
    "inputter": "Greg Beston",
    "input_time": "2002/05/13 3:58PM",
    "edit_time": "",
    "how_scored": "0",
    "pitches_entered": "0",
    "temperature": "0",
    "wind_direction": "0",
    "wind_speed": "-1",
    "field_condition": "0",
    "precipitation": "0",
    "sky": "0",
    "time_of_game": "126",
    "number_of_innings": "9",
    "visitor_final_score": "6",
    "home_final_score": "7",
    "visitor_hits": "10",
    "home_hits": "9",
    "visitor_errors": "1",
    "home_errors": "2",
    "visitor_left_on_base": "7",
    "home_left_on_base": "4",
    "winning_pitcher": "coopm101",
    "losing_pitcher": "gerha101",
    "save_for": "",
    "GW_RBI": "",
    "visitor_batter_1": "coscp101",
    "visitor_position_1": "4",
    "visitor_batter_2": "russj102",
    "visitor_position_2": "7",
    "visitor_batter_3": "giona101",
    "visitor_position_3": "8",
    "visitor_batter_4": "colmf101",
    "visitor_position_4": "3",
    "visitor_batter_5": "ellib103",
    "visitor_position_5": "5",
    "visitor_batter_6": "barrj106",
    "visitor_position_6": "9",
    "visitor_batter_7": "barnv102",
    "visitor_position_7": "6",
    "visitor_batter_8": "lopea102",
    "visitor_position_8": "2",
    "visitor_batter_9": "sewer101",
    "visitor_position_9": "1",
    "home_batter_1": "ramsb101",
    "home_position_1": "7",
    "home_batter_2": "culld101",
    "home_position_2": "6",
    "home_batter_3": "holmt101",
    "home_position_3": "9",
    "home_batter_4": "workc101",
    "home_position_4": "5",
    "home_batter_5": "masip101",
    "home_position_5": "2",
    "home_batter_6": "gillc102",
    "home_position_6": "8",
    "home_batter_7": "shupv101",
    "home_position_7": "3",
    "home_batter_8": "drewf101",
    "home_position_8": "4",
    "home_batter_9": "hutcj101",
    "home_position_9": "1",
    "field83": "gerha101",
    "field84": "coopm101"
  },
  {
    "game_id": "BSN194508031",
    "date": "19450803",
    "game_number": "1",
    "day_of_week": "Friday",
    "start_time": "0",
    "DH_used_flag": "F",
    "day_night_flag": "D",
    "visiting_team": "BRO",
    "home_team": "BSN",
    "game_site": "BOS08",
    "vis_starting_pitcher": "gregh102",
    "home_starting_pitcher": "tobij103",
    "home_plate_umpire": "mageg901",
    "first_base_umpire": "stewb901",
    "second_base_umpire": "(none)",
    "third_base_umpire": "balll901",
    "left_field_umpire": "",
    "right_field_umpire": "",
    "attendance": "0",
    "PS_scorer": "38",
    "translator": "Comly",
    "inputter": "Comly",
    "input_time": "2000/05/16 11:14PM",
    "edit_time": "",
    "how_scored": "1",
    "pitches_entered": "0",
    "temperature": "0",
    "wind_direction": "0",
    "wind_speed": "-1",
    "field_condition": "0",
    "precipitation": "0",
    "sky": "0",
    "time_of_game": "120",
    "number_of_innings": "9",
    "visitor_final_score": "5",
    "home_final_score": "1",
    "visitor_hits": "8",
    "home_hits": "1",
    "visitor_errors": "1",
    "home_errors": "1",
    "visitor_left_on_base": "9",
    "home_left_on_base": "2",
    "winning_pitcher": "gregh102",
    "losing_pitcher": "tobij103",
    "save_for": "",
    "GW_RBI": "",
    "visitor_batter_1": "stane101",
    "visitor_position_1": "4",
    "visitor_batter_2": "roseg101",
    "visitor_position_2": "8",
    "visitor_batter_3": "galaa101",
    "visitor_position_3": "3",
    "visitor_batter_4": "walkd101",
    "visitor_position_4": "9",
    "visitor_batter_5": "olmol101",
    "visitor_position_5": "7",
    "visitor_batter_6": "bordf101",
    "visitor_position_6": "5",
    "visitor_batter_7": "basie101",
    "visitor_position_7": "6",
    "visitor_batter_8": "dantf101",
    "visitor_position_8": "2",
    "visitor_batter_9": "gregh102",
    "visitor_position_9": "1",
    "home_batter_1": "culld101",
    "home_position_1": "6",
    "home_batter_2": "masip101",
    "home_position_2": "2",
    "home_batter_3": "holmt101",
    "home_position_3": "9",
    "home_batter_4": "medwj101",
    "home_position_4": "3",
    "home_batter_5": "niemb102",
    "home_position_5": "7",
    "home_batter_6": "gillc102",
    "home_position_6": "8",
    "home_batter_7": "workc101",
    "home_position_7": "5",
    "home_batter_8": "wietw101",
    "home_position_8": "4",
    "home_batter_9": "tobij103",
    "home_position_9": "1",
    "field83": "",
    "field84": ""
  },
  {
    "game_id": "BSN194508032",
    "date": "19450803",
    "game_number": "2",
    "day_of_week": "Friday",
    "start_time": "0",
    "DH_used_flag": "F",
    "day_night_flag": "D",
    "visiting_team": "BRO",
    "home_team": "BSN",
    "game_site": "BOS08",
    "vis_starting_pitcher": "branr103",
    "home_starting_pitcher": "wrige101",
    "home_plate_umpire": "stewb901",
    "first_base_umpire": "balll901",
    "second_base_umpire": "(none)",
    "third_base_umpire": "mageg901",
    "left_field_umpire": "",
    "right_field_umpire": "",
    "attendance": "6048",
    "PS_scorer": "38",
    "translator": "Comly",
    "inputter": "Comly",
    "input_time": "2000/05/16 11:28PM",
    "edit_time": "",
    "how_scored": "1",
    "pitches_entered": "0",
    "temperature": "0",
    "wind_direction": "0",
    "wind_speed": "-1",
    "field_condition": "0",
    "precipitation": "0",
    "sky": "0",
    "time_of_game": "0",
    "number_of_innings": "9",
    "visitor_final_score": "3",
    "home_final_score": "5",
    "visitor_hits": "13",
    "home_hits": "11",
    "visitor_errors": "0",
    "home_errors": "1",
    "visitor_left_on_base": "11",
    "home_left_on_base": "11",
    "winning_pitcher": "wrige101",
    "losing_pitcher": "branr103",
    "save_for": "",
    "GW_RBI": "",
    "visitor_batter_1": "stane101",
    "visitor_position_1": "4",
    "visitor_batter_2": "roseg101",
    "visitor_position_2": "8",
    "visitor_batter_3": "galaa101",
    "visitor_position_3": "3",
    "visitor_batter_4": "walkd101",
    "visitor_position_4": "9",
    "visitor_batter_5": "olmol101",
    "visitor_position_5": "7",
    "visitor_batter_6": "bordf101",
    "visitor_position_6": "5",
    "visitor_batter_7": "sandm101",
    "visitor_position_7": "2",
    "visitor_batter_8": "basie101",
    "visitor_position_8": "6",
    "visitor_batter_9": "branr103",
    "visitor_position_9": "1",
    "home_batter_1": "culld101",
    "home_position_1": "6",
    "home_batter_2": "wietw101",
    "home_position_2": "4",
    "home_batter_3": "holmt101",
    "home_position_3": "9",
    "home_batter_4": "medwj101",
    "home_position_4": "3",
    "home_batter_5": "niemb102",
    "home_position_5": "7",
    "home_batter_6": "gillc102",
    "home_position_6": "8",
    "home_batter_7": "workc101",
    "home_position_7": "5",
    "home_batter_8": "hoffs101",
    "home_position_8": "2",
    "home_batter_9": "wrige101",
    "home_position_9": "1",
    "field83": "seatt101",
    "field84": ""
  },
  {
    "game_id": "BSN194508040",
    "date": "19450804",
    "game_number": "0",
    "day_of_week": "Saturday",
    "start_time": "0",
    "DH_used_flag": "F",
    "day_night_flag": "D",
    "visiting_team": "BRO",
    "home_team": "BSN",
    "game_site": "BOS08",
    "vis_starting_pitcher": "lombv101",
    "home_starting_pitcher": "lee-b103",
    "home_plate_umpire": "balll901",
    "first_base_umpire": "mageg901",
    "second_base_umpire": "(none)",
    "third_base_umpire": "stewb901",
    "left_field_umpire": "",
    "right_field_umpire": "",
    "attendance": "4385",
    "PS_scorer": "38",
    "translator": "Comly",
    "inputter": "Comly",
    "input_time": "2000/05/16 11:40PM",
    "edit_time": "",
    "how_scored": "1",
    "pitches_entered": "0",
    "temperature": "0",
    "wind_direction": "0",
    "wind_speed": "-1",
    "field_condition": "0",
    "precipitation": "0",
    "sky": "0",
    "time_of_game": "104",
    "number_of_innings": "9",
    "visitor_final_score": "0",
    "home_final_score": "1",
    "visitor_hits": "6",
    "home_hits": "4",
    "visitor_errors": "0",
    "home_errors": "0",
    "visitor_left_on_base": "4",
    "home_left_on_base": "6",
    "winning_pitcher": "lee-b103",
    "losing_pitcher": "lombv101",
    "save_for": "",
    "GW_RBI": "",
    "visitor_batter_1": "stane101",
    "visitor_position_1": "4",
    "visitor_batter_2": "roseg101",
    "visitor_position_2": "8",
    "visitor_batter_3": "galaa101",
    "visitor_position_3": "3",
    "visitor_batter_4": "walkd101",
    "visitor_position_4": "9",
    "visitor_batter_5": "olmol101",
    "visitor_position_5": "7",
    "visitor_batter_6": "bordf101",
    "visitor_position_6": "5",
    "visitor_batter_7": "peacj101",
    "visitor_position_7": "2",
    "visitor_batter_8": "basie101",
    "visitor_position_8": "6",
    "visitor_batter_9": "lombv101",
    "visitor_position_9": "1",
    "home_batter_1": "culld101",
    "home_position_1": "6",
    "home_batter_2": "masip101",
    "home_position_2": "2",
    "home_batter_3": "holmt101",
    "home_position_3": "9",
    "home_batter_4": "medwj101",
    "home_position_4": "3",
    "home_batter_5": "niemb102",
    "home_position_5": "7",
    "home_batter_6": "gillc102",
    "home_position_6": "8",
    "home_batter_7": "workc101",
    "home_position_7": "5",
    "home_batter_8": "wietw101",
    "home_position_8": "4",
    "home_batter_9": "lee-b103",
    "home_position_9": "1",
    "field83": "bukec101",
    "field84": ""
  },
  {
    "game_id": "BSN194508051",
    "date": "19450805",
    "game_number": "1",
    "day_of_week": "Sunday",
    "start_time": "0",
    "DH_used_flag": "F",
    "day_night_flag": "D",
    "visiting_team": "BRO",
    "home_team": "BSN",
    "game_site": "BOS08",
    "vis_starting_pitcher": "herra101",
    "home_starting_pitcher": "javea101",
    "home_plate_umpire": "mageg901",
    "first_base_umpire": "stewb901",
    "second_base_umpire": "(none)",
    "third_base_umpire": "balll901",
    "left_field_umpire": "",
    "right_field_umpire": "",
    "attendance": "0",
    "PS_scorer": "38",
    "translator": "Comly",
    "inputter": "Comly",
    "input_time": "2000/05/16 11:50PM",
    "edit_time": "",
    "how_scored": "1",
    "pitches_entered": "0",
    "temperature": "0",
    "wind_direction": "0",
    "wind_speed": "-1",
    "field_condition": "0",
    "precipitation": "0",
    "sky": "0",
    "time_of_game": "116",
    "number_of_innings": "9",
    "visitor_final_score": "7",
    "home_final_score": "0",
    "visitor_hits": "12",
    "home_hits": "2",
    "visitor_errors": "0",
    "home_errors": "0",
    "visitor_left_on_base": "7",
    "home_left_on_base": "4",
    "winning_pitcher": "herra101",
    "losing_pitcher": "javea101",
    "save_for": "",
    "GW_RBI": "",
    "visitor_batter_1": "stane101",
    "visitor_position_1": "4",
    "visitor_batter_2": "roseg101",
    "visitor_position_2": "8",
    "visitor_batter_3": "galaa101",
    "visitor_position_3": "3",
    "visitor_batter_4": "walkd101",
    "visitor_position_4": "9",
    "visitor_batter_5": "olmol101",
    "visitor_position_5": "7",
    "visitor_batter_6": "bordf101",
    "visitor_position_6": "5",
    "visitor_batter_7": "browt103",
    "visitor_position_7": "6",
    "visitor_batter_8": "peacj101",
    "visitor_position_8": "2",
    "visitor_batter_9": "herra101",
    "visitor_position_9": "1",
    "home_batter_1": "culld101",
    "home_position_1": "6",
    "home_batter_2": "masip101",
    "home_position_2": "2",
    "home_batter_3": "holmt101",
    "home_position_3": "9",
    "home_batter_4": "medwj101",
    "home_position_4": "3",
    "home_batter_5": "niemb102",
    "home_position_5": "7",
    "home_batter_6": "gillc102",
    "home_position_6": "8",
    "home_batter_7": "workc101",
    "home_position_7": "5",
    "home_batter_8": "wietw101",
    "home_position_8": "4",
    "home_batter_9": "javea101",
    "home_position_9": "1",
    "field83": "",
    "field84": "hevij101"
  },
  {
    "game_id": "BSN194508052",
    "date": "19450805",
    "game_number": "2",
    "day_of_week": "Sunday",
    "start_time": "0",
    "DH_used_flag": "F",
    "day_night_flag": "D",
    "visiting_team": "BRO",
    "home_team": "BSN",
    "game_site": "BOS08",
    "vis_starting_pitcher": "davic103",
    "home_starting_pitcher": "logab101",
    "home_plate_umpire": "stewb901",
    "first_base_umpire": "balll901",
    "second_base_umpire": "(none)",
    "third_base_umpire": "mageg901",
    "left_field_umpire": "",
    "right_field_umpire": "",
    "attendance": "21068",
    "PS_scorer": "38",
    "translator": "Comly",
    "inputter": "Comly",
    "input_time": "2000/05/17 12:01AM",
    "edit_time": "",
    "how_scored": "1",
    "pitches_entered": "0",
    "temperature": "0",
    "wind_direction": "0",
    "wind_speed": "-1",
    "field_condition": "0",
    "precipitation": "0",
    "sky": "0",
    "time_of_game": "123",
    "number_of_innings": "9",
    "visitor_final_score": "1",
    "home_final_score": "10",
    "visitor_hits": "11",
    "home_hits": "16",
    "visitor_errors": "0",
    "home_errors": "1",
    "visitor_left_on_base": "12",
    "home_left_on_base": "8",
    "winning_pitcher": "logab101",
    "losing_pitcher": "davic103",
    "save_for": "",
    "GW_RBI": "",
    "visitor_batter_1": "stane101",
    "visitor_position_1": "4",
    "visitor_batter_2": "roseg101",
    "visitor_position_2": "8",
    "visitor_batter_3": "galaa101",
    "visitor_position_3": "3",
    "visitor_batter_4": "walkd101",
    "visitor_position_4": "9",
    "visitor_batter_5": "olmol101",
    "visitor_position_5": "7",
    "visitor_batter_6": "bordf101",
    "visitor_position_6": "5",
    "visitor_batter_7": "browt103",
    "visitor_position_7": "6",
    "visitor_batter_8": "dantf101",
    "visitor_position_8": "2",
    "visitor_batter_9": "davic103",
    "visitor_position_9": "1",
    "home_batter_1": "culld101",
    "home_position_1": "6",
    "home_batter_2": "wietw101",
    "home_position_2": "4",
    "home_batter_3": "holmt101",
    "home_position_3": "9",
    "home_batter_4": "medwj101",
    "home_position_4": "3",
    "home_batter_5": "niemb102",
    "home_position_5": "7",
    "home_batter_6": "gillc102",
    "home_position_6": "8",
    "home_batter_7": "workc101",
    "home_position_7": "5",
    "home_batter_8": "hoffs101",
    "home_position_8": "2",
    "home_batter_9": "logab101",
    "home_position_9": "1",
    "field83": "bukec101",
    "field84": ""
  },
  {
    "game_id": "BSN194508081",
    "date": "19450808",
    "game_number": "1",
    "day_of_week": "Wednesday",
    "start_time": "0",
    "DH_used_flag": "F",
    "day_night_flag": "D",
    "visiting_team": "CHN",
    "home_team": "BSN",
    "game_site": "BOS08",
    "vis_starting_pitcher": "primr101",
    "home_starting_pitcher": "andrn101",
    "home_plate_umpire": "pineb101",
    "first_base_umpire": "conlj102",
    "second_base_umpire": "(none)",
    "third_base_umpire": "boggd901",
    "left_field_umpire": "",
    "right_field_umpire": "",
    "attendance": "0",
    "PS_scorer": "115",
    "translator": "Bob Kistler",
    "inputter": "Greg Beston",
    "input_time": "2002/05/13 7:53PM",
    "edit_time": "",
    "how_scored": "0",
    "pitches_entered": "0",
    "temperature": "0",
    "wind_direction": "0",
    "wind_speed": "-1",
    "field_condition": "0",
    "precipitation": "0",
    "sky": "0",
    "time_of_game": "126",
    "number_of_innings": "9",
    "visitor_final_score": "5",
    "home_final_score": "2",
    "visitor_hits": "16",
    "home_hits": "5",
    "visitor_errors": "1",
    "home_errors": "1",
    "visitor_left_on_base": "13",
    "home_left_on_base": "5",
    "winning_pitcher": "primr101",
    "losing_pitcher": "andrn101",
    "save_for": "",
    "GW_RBI": "",
    "visitor_batter_1": "hacks101",
    "visitor_position_1": "5",
    "visitor_batter_2": "johnd101",
    "visitor_position_2": "4",
    "visitor_batter_3": "lowrp101",
    "visitor_position_3": "7",
    "visitor_batter_4": "cavap101",
    "visitor_position_4": "3",
    "visitor_batter_5": "pafka101",
    "visitor_position_5": "8",
    "visitor_batter_6": "nichb101",
    "visitor_position_6": "9",
    "visitor_batter_7": "gillp103",
    "visitor_position_7": "2",
    "visitor_batter_8": "merul101",
    "visitor_position_8": "6",
    "visitor_batter_9": "primr101",
    "visitor_position_9": "1",
    "home_batter_1": "culld101",
    "home_position_1": "6",
    "home_batter_2": "wietw101",
    "home_position_2": "4",
    "home_batter_3": "holmt101",
    "home_position_3": "9",
    "home_batter_4": "medwj101",
    "home_position_4": "3",
    "home_batter_5": "niemb102",
    "home_position_5": "7",
    "home_batter_6": "gillc102",
    "home_position_6": "8",
    "home_batter_7": "workc101",
    "home_position_7": "5",
    "home_batter_8": "hoffs101",
    "home_position_8": "2",
    "home_batter_9": "andrn101",
    "home_position_9": "1",
    "field83": "",
    "field84": "hutcj101"
  },
  {
    "game_id": "BSN194508110",
    "date": "19450811",
    "game_number": "0",
    "day_of_week": "Saturday",
    "start_time": "0",
    "DH_used_flag": "F",
    "day_night_flag": "D",
    "visiting_team": "CHN",
    "home_team": "BSN",
    "game_site": "BOS08",
    "vis_starting_pitcher": "passc101",
    "home_starting_pitcher": "logab101",
    "home_plate_umpire": "conlj102",
    "first_base_umpire": "boggd901",
    "second_base_umpire": "(none)",
    "third_base_umpire": "pineb101",
    "left_field_umpire": "",
    "right_field_umpire": "",
    "attendance": "4612",
    "PS_scorer": "115",
    "translator": "Bob Kistler",
    "inputter": "Greg Beston",
    "input_time": "2002/05/20 8:32PM",
    "edit_time": "",
    "how_scored": "0",
    "pitches_entered": "0",
    "temperature": "0",
    "wind_direction": "0",
    "wind_speed": "-1",
    "field_condition": "0",
    "precipitation": "0",
    "sky": "0",
    "time_of_game": "137",
    "number_of_innings": "9",
    "visitor_final_score": "8",
    "home_final_score": "0",
    "visitor_hits": "11",
    "home_hits": "2",
    "visitor_errors": "1",
    "home_errors": "3",
    "visitor_left_on_base": "15",
    "home_left_on_base": "3",
    "winning_pitcher": "passc101",
    "losing_pitcher": "logab101",
    "save_for": "",
    "GW_RBI": "",
    "visitor_batter_1": "hacks101",
    "visitor_position_1": "5",
    "visitor_batter_2": "johnd101",
    "visitor_position_2": "4",
    "visitor_batter_3": "lowrp101",
    "visitor_position_3": "7",
    "visitor_batter_4": "cavap101",
    "visitor_position_4": "3",
    "visitor_batter_5": "pafka101",
    "visitor_position_5": "8",
    "visitor_batter_6": "nichb101",
    "visitor_position_6": "9",
    "visitor_batter_7": "ricel101",
    "visitor_position_7": "2",
    "visitor_batter_8": "merul101",
    "visitor_position_8": "6",
    "visitor_batter_9": "passc101",
    "visitor_position_9": "1",
    "home_batter_1": "nelst101",
    "home_position_1": "4",
    "home_batter_2": "shupv101",
    "home_position_2": "3",
    "home_batter_3": "holmt101",
    "home_position_3": "9",
    "home_batter_4": "niemb102",
    "home_position_4": "7",
    "home_batter_5": "workc101",
    "home_position_5": "5",
    "home_batter_6": "gillc102",
    "home_position_6": "8",
    "home_batter_7": "masip101",
    "home_position_7": "2",
    "home_batter_8": "culld101",
    "home_position_8": "6",
    "home_batter_9": "logab101",
    "home_position_9": "1",
    "field83": "",
    "field84": "hendd101"
  },
  {
    "game_id": "BSN194508141",
    "date": "19450814",
    "game_number": "1",
    "day_of_week": "Tuesday",
    "start_time": "0",
    "DH_used_flag": "F",
    "day_night_flag": "D",
    "visiting_team": "PIT",
    "home_team": "BSN",
    "game_site": "BOS08",
    "vis_starting_pitcher": "ostef101",
    "home_starting_pitcher": "lee-b103",
    "home_plate_umpire": "searz901",
    "first_base_umpire": "barrg901",
    "second_base_umpire": "(none)",
    "third_base_umpire": "dunnt901",
    "left_field_umpire": "",
    "right_field_umpire": "",
    "attendance": "0",
    "PS_scorer": "115",
    "translator": "Bob Kistler",
    "inputter": "Greg Beston",
    "input_time": "2002/05/21 6:31PM",
    "edit_time": "",
    "how_scored": "0",
    "pitches_entered": "0",
    "temperature": "0",
    "wind_direction": "0",
    "wind_speed": "-1",
    "field_condition": "0",
    "precipitation": "0",
    "sky": "0",
    "time_of_game": "134",
    "number_of_innings": "10",
    "visitor_final_score": "7",
    "home_final_score": "5",
    "visitor_hits": "13",
    "home_hits": "9",
    "visitor_errors": "2",
    "home_errors": "0",
    "visitor_left_on_base": "9",
    "home_left_on_base": "5",
    "winning_pitcher": "ostef101",
    "losing_pitcher": "hendd101",
    "save_for": "",
    "GW_RBI": "",
    "visitor_batter_1": "gustf101",
    "visitor_position_1": "4",
    "visitor_batter_2": "giona101",
    "visitor_position_2": "8",
    "visitor_batter_3": "russj102",
    "visitor_position_3": "7",
    "visitor_batter_4": "ellib103",
    "visitor_position_4": "5",
    "visitor_batter_5": "barrj106",
    "visitor_position_5": "9",
    "visitor_batter_6": "dahlb101",
    "visitor_position_6": "3",
    "visitor_batter_7": "barnv102",
    "visitor_position_7": "6",
    "visitor_batter_8": "lopea102",
    "visitor_position_8": "2",
    "visitor_batter_9": "ostef101",
    "visitor_position_9": "1",
    "home_batter_1": "nelst101",
    "home_position_1": "4",
    "home_batter_2": "shupv101",
    "home_position_2": "3",
    "home_batter_3": "holmt101",
    "home_position_3": "9",
    "home_batter_4": "medwj101",
    "home_position_4": "7",
    "home_batter_5": "workc101",
    "home_position_5": "5",
    "home_batter_6": "gillc102",
    "home_position_6": "8",
    "home_batter_7": "masip101",
    "home_position_7": "2",
    "home_batter_8": "culld101",
    "home_position_8": "6",
    "home_batter_9": "lee-b103",
    "home_position_9": "1",
    "field83": "",
    "field84": "hendd101"
  },
  {
    "game_id": "BSN194508161",
    "date": "19450816",
    "game_number": "1",
    "day_of_week": "Thursday",
    "start_time": "0",
    "DH_used_flag": "F",
    "day_night_flag": "D",
    "visiting_team": "CIN",
    "home_team": "BSN",
    "game_site": "BOS08",
    "vis_starting_pitcher": "bowmj101",
    "home_starting_pitcher": "hutcj101",
    "home_plate_umpire": "mageg901",
    "first_base_umpire": "stewb901",
    "second_base_umpire": "(none)",
    "third_base_umpire": "balll901",
    "left_field_umpire": "",
    "right_field_umpire": "",
    "attendance": "0",
    "PS_scorer": "115",
    "translator": "Bob Kistler",
    "inputter": "Greg Beston",
    "input_time": "2002/05/26 12:44PM",
    "edit_time": "",
    "how_scored": "0",
    "pitches_entered": "0",
    "temperature": "0",
    "wind_direction": "0",
    "wind_speed": "-1",
    "field_condition": "0",
    "precipitation": "0",
    "sky": "0",
    "time_of_game": "115",
    "number_of_innings": "9",
    "visitor_final_score": "5",
    "home_final_score": "3",
    "visitor_hits": "9",
    "home_hits": "9",
    "visitor_errors": "1",
    "home_errors": "1",
    "visitor_left_on_base": "4",
    "home_left_on_base": "6",
    "winning_pitcher": "bowmj101",
    "losing_pitcher": "hutcj101",
    "save_for": "",
    "GW_RBI": "",
    "visitor_batter_1": "clayd101",
    "visitor_position_1": "8",
    "visitor_batter_2": "willw101",
    "visitor_position_2": "4",
    "visitor_batter_3": "libka101",
    "visitor_position_3": "9",
    "visitor_batter_4": "mccof101",
    "visitor_position_4": "3",
    "visitor_batter_5": "tipte101",
    "visitor_position_5": "7",
    "visitor_batter_6": "mille104",
    "visitor_position_6": "6",
    "visitor_batter_7": "mesns101",
    "visitor_position_7": "5",
    "visitor_batter_8": "unsea101",
    "visitor_position_8": "2",
    "visitor_batter_9": "bowmj101",
    "visitor_position_9": "1",
    "home_batter_1": "wietw101",
    "home_position_1": "4",
    "home_batter_2": "shupv101",
    "home_position_2": "3",
    "home_batter_3": "holmt101",
    "home_position_3": "9",
    "home_batter_4": "aderm101",
    "home_position_4": "7",
    "home_batter_5": "workc101",
    "home_position_5": "5",
    "home_batter_6": "ramsb101",
    "home_position_6": "8",
    "home_batter_7": "hoffs101",
    "home_position_7": "2",
    "home_batter_8": "culld101",
    "home_position_8": "6",
    "home_batter_9": "hutcj101",
    "home_position_9": "1",
    "field83": "",
    "field84": "hendd101"
  }
]